boltpy/__init__.py
boltpy/core.py
boltpy-0.1.7.dist-info/METADATA
boltpy-0.1.7.dist-info/WHEEL
boltpy-0.1.7.dist-info/licenses/LICENSE
boltpy-0.1.7.dist-info/RECORD
