Metadata-Version: 2.4
Name: boltpy
Version: 0.1.7
Summary: BOLT: Bibliographic Orchestration for Literature Triage
License: MIT License
License-File: LICENSE
Keywords: bibliography,literature-review,metadata,research,scraping,systematic-review
Classifier: Development Status :: 3 - Alpha
Classifier: Intended Audience :: Science/Research
Classifier: License :: OSI Approved :: MIT License
Classifier: Programming Language :: Python :: 3
Classifier: Programming Language :: Python :: 3 :: Only
Classifier: Programming Language :: Python :: 3.10
Classifier: Programming Language :: Python :: 3.11
Classifier: Programming Language :: Python :: 3.12
Classifier: Topic :: Scientific/Engineering :: Information Analysis
Classifier: Topic :: Text Processing :: General
Requires-Python: >=3.10
Requires-Dist: feedparser>=6.0
Requires-Dist: pandas>=2.0
Requires-Dist: rapidfuzz>=3.0
Requires-Dist: requests>=2.31
Provides-Extra: dev
Requires-Dist: build>=1.2; extra == 'dev'
Requires-Dist: mypy>=1.10; extra == 'dev'
Requires-Dist: pytest>=8; extra == 'dev'
Requires-Dist: ruff>=0.6; extra == 'dev'
Requires-Dist: twine>=5.1; extra == 'dev'
